easytelemetry/README.md
easytelemetry/__init__.py
easytelemetry/appinsights/__init__.py
easytelemetry/appinsights/protocol.py
easytelemetry/inmemory.py
easytelemetry/py.typed
easytelemetry-1.0.0.dist-info/LICENSE
easytelemetry-1.0.0.dist-info/METADATA
easytelemetry-1.0.0.dist-info/WHEEL
easytelemetry-1.0.0.dist-info/RECORD
