Metadata-Version: 2.1
Name: easytelemetry
Version: 1.0.0
Summary: Telemetry package (logging and metrics) with minimal and opinionated API using Application Insights as back-end.
Home-page: https://github.com/jdvor/easytelemetry
License: MIT
Keywords: azure,application insights,telemetry,logging
Author: jan Dvorak
Author-email: jandvorak.public@gmail.com
Requires-Python: >=3.12,<4.0
Classifier: License :: OSI Approved :: MIT License
Classifier: Programming Language :: Python :: 3
Classifier: Programming Language :: Python :: 3.12
Classifier: Programming Language :: Python :: 3.13
Requires-Dist: orjson (>=3.10.11,<4.0.0)
Requires-Dist: requests (>=2.32.3,<3.0.0)
Project-URL: Bug Tracker, https://github.com/jdvor/easytelemetry/issues
Project-URL: Repository, https://github.com/jdvor/easytelemetry
